WMCore/Configuration.py
WMCore/Lexicon.py
WMCore/WMException.py
WMCore/__init__.py
WMCore/ACDC/Collection.py
WMCore/ACDC/CollectionTypes.py
WMCore/ACDC/CouchCollection.py
WMCore/ACDC/CouchFileset.py
WMCore/ACDC/CouchService.py
WMCore/ACDC/DataCollectionService.py
WMCore/ACDC/Fileset.py
WMCore/ACDC/__init__.py
WMCore/Algorithms/ParseXMLFile.py
WMCore/Algorithms/Permissions.py
WMCore/Algorithms/__init__.py
WMCore/DataStructs/File.py
WMCore/DataStructs/Fileset.py
WMCore/DataStructs/Job.py
WMCore/DataStructs/JobGroup.py
WMCore/DataStructs/JobPackage.py
WMCore/DataStructs/LumiList.py
WMCore/DataStructs/Mask.py
WMCore/DataStructs/Pickleable.py
WMCore/DataStructs/Run.py
WMCore/DataStructs/Subscription.py
WMCore/DataStructs/WMObject.py
WMCore/DataStructs/WorkUnit.py
WMCore/DataStructs/Workflow.py
WMCore/DataStructs/__init__.py
WMCore/Database/CMSCouch.py
WMCore/Database/ConfigDBMap.py
WMCore/Database/CouchMonitoring.py
WMCore/Database/CouchUtils.py
WMCore/Database/DBCore.py
WMCore/Database/DBCreator.py
WMCore/Database/DBExceptionHandler.py
WMCore/Database/DBFactory.py
WMCore/Database/DBFormatter.py
WMCore/Database/Dialects.py
WMCore/Database/ExecuteDAO.py
WMCore/Database/MongoDB.py
WMCore/Database/MySQLCore.py
WMCore/Database/ResultSet.py
WMCore/Database/Transaction.py
WMCore/Database/__init__.py
WMCore/Database/ipy_profile_couch.py
WMCore/GroupUser/CouchObject.py
WMCore/GroupUser/Decorators.py
WMCore/GroupUser/Group.py
WMCore/GroupUser/Interface.py
WMCore/GroupUser/User.py
WMCore/GroupUser/__init__.py
WMCore/Services/Requests.py
WMCore/Services/__init__.py
WMCore/Services/pycurl_manager.py
WMCore/Wrappers/__init__.py
WMCore/Wrappers/JsonWrapper/JSONThunker.py
WMCore/Wrappers/JsonWrapper/__init__.py
acdcserver-2.4.5.3.data/data/data/couchapps/ACDC/_id
acdcserver-2.4.5.3.data/data/data/couchapps/ACDC/couchapp.json
acdcserver-2.4.5.3.data/data/data/couchapps/ACDC/rewrites.json
acdcserver-2.4.5.3.data/data/data/couchapps/ACDC/validate_doc_update.js
acdcserver-2.4.5.3.dist-info/licenses/LICENSE
acdcserver-2.4.5.3.dist-info/licenses/NOTICE
acdcserver-2.4.5.3.dist-info/METADATA
acdcserver-2.4.5.3.dist-info/WHEEL
acdcserver-2.4.5.3.dist-info/top_level.txt
acdcserver-2.4.5.3.dist-info/RECORD
