Metadata-Version: 2.4
Name: acdcserver
Version: 2.4.5.3
Home-page: https://github.com/dmwm/WMCore
Maintainer: CMS DMWM Group
Maintainer-email: hn-cms-wmdevelopment@cern.ch
License: Apache License, Version 2.0
License-File: LICENSE
License-File: NOTICE
Requires-Dist: future~=1.0.0
Requires-Dist: httplib2~=0.22.0
Requires-Dist: Sphinx~=5.3.0
Requires-Dist: PyJWT~=2.9.0
Dynamic: home-page
Dynamic: license
Dynamic: license-file
Dynamic: maintainer
Dynamic: maintainer-email
Dynamic: requires-dist
